nodalize/__init__.py
nodalize/datanode.py
nodalize/dependency.py
nodalize/dependency_loader.py
nodalize/calculators/__init__.py
nodalize/calculators/calculator.py
nodalize/calculators/dask_calculator.py
nodalize/calculators/pandas_calculator.py
nodalize/calculators/polars_calculator.py
nodalize/calculators/pyarrow_calculator.py
nodalize/calculators/spark_calculator.py
nodalize/constants/__init__.py
nodalize/constants/column_category.py
nodalize/constants/column_names.py
nodalize/constants/custom_types.py
nodalize/custom_dependencies/__init__.py
nodalize/custom_dependencies/date.py
nodalize/custom_dependencies/lag.py
nodalize/custom_dependencies/window.py
nodalize/data_management/__init__.py
nodalize/data_management/data_manager.py
nodalize/data_management/database_data_manager.py
nodalize/data_management/delta_lake_data_manager.py
nodalize/data_management/duckdb_data_manager.py
nodalize/data_management/kdb_data_manager.py
nodalize/data_management/local_file_data_manager.py
nodalize/data_management/s3_file_data_manager.py
nodalize/data_management/sqlite_data_manager.py
nodalize/orchestration/__init__.py
nodalize/orchestration/calculator_factory.py
nodalize/orchestration/coordinator.py
nodalize/orchestration/data_manager_factory.py
nodalize/orchestration/data_node_cache.py
nodalize/tools/__init__.py
nodalize/tools/dates.py
nodalize/tools/static_func_tools.py
nodalize/tools/tree.py
sandbox/__init__.py
sandbox/test_anything.py
nodalize-1.0.3.dist-info/LICENSE
nodalize-1.0.3.dist-info/METADATA
nodalize-1.0.3.dist-info/WHEEL
nodalize-1.0.3.dist-info/top_level.txt
nodalize-1.0.3.dist-info/RECORD
