Metadata-Version: 2.1
Name: nodalize
Version: 1.0.3
Summary: Framework to organize data transformation flow.
Home-page: https://github.com/Ron-Ldn/nodalize
Author: Ronan Mouquet
Author-email: ronan.mouquet@gmail.com
License: MIT
Platform: UNKNOWN
License-File: LICENSE
